MANIFEST.in
README.md
setup.cfg
setup.py
pyhadoop/__init__.py
pyhadoop/__main__.py
pyhadoop/resources.py
pyhadoop.egg-info/PKG-INFO
pyhadoop.egg-info/SOURCES.txt
pyhadoop.egg-info/dependency_links.txt
pyhadoop.egg-info/entry_points.txt
pyhadoop.egg-info/top_level.txt