Metadata-Version: 1.1
Name: pyhadoop
Version: 0.1
Summary: Python based hadoop command-line interface
Home-page: https://github.com/mehikmat/PyHadoop
Author: mehikmat
Author-email: me.hemant.available@gmail.com
License: MIT
Download-URL: https://github.com/mehikmat/PyHadoop/tarball/0.1
Keywords: hadoop,python,command-line
Platform: any
Classifier: Development Status :: 5 - Production/Stable
Classifier: Topic :: Utilities
Classifier: License :: OSI Approved :: MIT License
